investing_algorithm_framework/__init__.py
investing_algorithm_framework/analysis/__init__.py
investing_algorithm_framework/analysis/backtest_data_ranges.py
investing_algorithm_framework/analysis/data.py
investing_algorithm_framework/analysis/markdown.py
investing_algorithm_framework/analysis/ranking.py
investing_algorithm_framework/app/__init__.py
investing_algorithm_framework/app/algorithm/__init__.py
investing_algorithm_framework/app/algorithm/algorithm.py
investing_algorithm_framework/app/algorithm/algorithm_factory.py
investing_algorithm_framework/app/app.py
investing_algorithm_framework/app/app_hook.py
investing_algorithm_framework/app/context.py
investing_algorithm_framework/app/eventloop.py
investing_algorithm_framework/app/reporting/__init__.py
investing_algorithm_framework/app/reporting/ascii.py
investing_algorithm_framework/app/reporting/backtest_report.py
investing_algorithm_framework/app/reporting/charts/__init__.py
investing_algorithm_framework/app/reporting/charts/entry_exist_signals.py
investing_algorithm_framework/app/reporting/charts/equity_curve.py
investing_algorithm_framework/app/reporting/charts/equity_curve_drawdown.py
investing_algorithm_framework/app/reporting/charts/line_chart.py
investing_algorithm_framework/app/reporting/charts/monthly_returns_heatmap.py
investing_algorithm_framework/app/reporting/charts/ohlcv_data_completeness.py
investing_algorithm_framework/app/reporting/charts/rolling_sharp_ratio.py
investing_algorithm_framework/app/reporting/charts/yearly_returns_barchart.py
investing_algorithm_framework/app/reporting/generate.py
investing_algorithm_framework/app/reporting/tables/__init__.py
investing_algorithm_framework/app/reporting/tables/key_metrics_table.py
investing_algorithm_framework/app/reporting/tables/stop_loss_table.py
investing_algorithm_framework/app/reporting/tables/time_metrics_table.py
investing_algorithm_framework/app/reporting/tables/trade_metrics_table.py
investing_algorithm_framework-7.25.6.dist-info/LICENSE
investing_algorithm_framework-7.25.6.dist-info/METADATA
investing_algorithm_framework-7.25.6.dist-info/WHEEL
investing_algorithm_framework-7.25.6.dist-info/entry_points.txt
investing_algorithm_framework-7.25.6.dist-info/RECORD
