Metadata-Version: 2.1
Name: investing-algorithm-framework
Version: 7.25.6
Summary: A framework for creating trading bots
Author: MDUYN
Requires-Python: >=3.10
Classifier: Programming Language :: Python :: 3
Classifier: Programming Language :: Python :: 3.10
Classifier: Programming Language :: Python :: 3.11
Classifier: Programming Language :: Python :: 3.12
Requires-Dist: Flask (>=3.1.0)
Requires-Dist: Flask-Cors (>=3.0.9,<5.0.0)
Requires-Dist: Flask-Migrate (>=2.6.0)
Requires-Dist: SQLAlchemy (>=2.0.18)
Requires-Dist: azure-identity (>=1.19.0,<2.0.0)
Requires-Dist: azure-mgmt-resource (>=23.2.0,<24.0.0)
Requires-Dist: azure-mgmt-storage (>=21.2.1,<22.0.0)
Requires-Dist: azure-mgmt-web (>=7.3.1,<8.0.0)
Requires-Dist: azure-storage-blob (>=12.24.0,<13.0.0)
Requires-Dist: boto3 (>=1.38.41,<2.0.0)
Requires-Dist: ccxt (>=4.2.48)
Requires-Dist: dependency-injector (>=4.40.0)
Requires-Dist: jupyter (>=1.0.0)
Requires-Dist: marshmallow (>=3.5.0)
Requires-Dist: plotly (>=6.1.2,<7.0.0)
Requires-Dist: polars[numpy,pandas] (>=0.20.10)
Requires-Dist: python-dateutil (>=2.8.2)
Requires-Dist: python-dotenv (>=1.0.1,<2.0.0)
Requires-Dist: schedule (>=1.1.0)
Requires-Dist: tabulate (>=0.9.0)
Requires-Dist: tqdm (>=4.66.1)
Requires-Dist: wrapt (>=1.16.0)
Requires-Dist: yfinance (>=0.2.61,<0.3.0)
